setup.py
claims_helper/__init__.py
claims_helper/claims_helper.py
claims_helper/permissions.py
claims_helper.egg-info/PKG-INFO
claims_helper.egg-info/SOURCES.txt
claims_helper.egg-info/dependency_links.txt
claims_helper.egg-info/not-zip-safe
claims_helper.egg-info/requires.txt
claims_helper.egg-info/top_level.txt