Metadata-Version: 1.0
Name: claims-helper
Version: 0.1.4
Summary: Decodes roles from custom claims
Home-page: UNKNOWN
Author: Blaze devices
Author-email: devices@blaze.cc
License: MIT
Platform: UNKNOWN
